panfig/__init__.py
panfig/__main__.py
panfig/_types.py
panfig/aliases.py
panfig/errors.py
panfig/panfigblock.py
panfig-0.1.1.dist-info/DESCRIPTION.rst
panfig-0.1.1.dist-info/METADATA
panfig-0.1.1.dist-info/RECORD
panfig-0.1.1.dist-info/WHEEL
panfig-0.1.1.dist-info/entry_points.txt
panfig-0.1.1.dist-info/metadata.json
panfig-0.1.1.dist-info/top_level.txt
