Metadata-Version: 2.0
Name: panfig
Version: 0.1.1
Summary: A framework for describing figures in Pandoc documents
Home-page: https://github.com/speezepearson/panfig
Author: speezepearson
Author-email: speeze.pearson+1098@gmail.com
License: UNKNOWN
Keywords: pandoc pandocfilters
Platform: UNKNOWN
Classifier: Development Status :: 3 - Alpha
Classifier: Programming Language :: Python :: 3
Classifier: Programming Language :: Python :: 3.2
Classifier: Programming Language :: Python :: 3.3
Classifier: Programming Language :: Python :: 3.4
Requires-Dist: pandocfilters
Provides-Extra: dev
Provides-Extra: test
